sinapsis_langchain-0.2.6.dist-info/licenses/LICENSE
sinapsis_langchain_readers/src/sinapsis_langchain_readers/__init__.py
sinapsis_langchain_readers/src/sinapsis_langchain_readers/helpers/__init__.py
sinapsis_langchain_readers/src/sinapsis_langchain_readers/helpers/excluded_loader_modules_objects.py
sinapsis_langchain_readers/src/sinapsis_langchain_readers/helpers/include_modules_no_force_init.py
sinapsis_langchain_readers/src/sinapsis_langchain_readers/helpers/include_modules_no_kwargs.py
sinapsis_langchain_readers/src/sinapsis_langchain_readers/helpers/tags.py
sinapsis_langchain_readers/src/sinapsis_langchain_readers/templates/__init__.py
sinapsis_langchain_readers/src/sinapsis_langchain_readers/templates/base_static_loader.py
sinapsis_langchain_readers/src/sinapsis_langchain_readers/templates/langchain_data_readers.py
sinapsis_langchain_readers/src/sinapsis_langchain_readers/templates/langchain_data_readers_no_force_init.py
sinapsis_langchain_readers/src/sinapsis_langchain_readers/templates/langchain_data_readers_no_kwgars.py
sinapsis_langchain_readers/src/sinapsis_langchain_readers/templates/one_drive_file_loader.py
sinapsis_langchain_splitters/src/__init__.py
sinapsis_langchain_splitters/src/sinapsis_langchain_splitters/helpers/__init__.py
sinapsis_langchain_splitters/src/sinapsis_langchain_splitters/helpers/tags.py
sinapsis_langchain_splitters/src/sinapsis_langchain_splitters/templates/__init__.py
sinapsis_langchain_splitters/src/sinapsis_langchain_splitters/templates/langchain_text_splitters.py
sinapsis_langchain-0.2.6.dist-info/METADATA
sinapsis_langchain-0.2.6.dist-info/WHEEL
sinapsis_langchain-0.2.6.dist-info/top_level.txt
sinapsis_langchain-0.2.6.dist-info/RECORD
