Metadata-Version: 2.4
Name: sinapsis-langchain
Version: 0.2.6
Summary: Sinapsis module that adds support for the Langchain library
Author-email: SinapsisAI <dev@sinapsis.tech>
Project-URL: Homepage, https://sinapsis.tech
Project-URL: Documentation, https://docs.sinapsis.tech/docs
Project-URL: Tutorials, https://docs.sinapsis.tech/tutorials
Project-URL: Repository, https://github.com/Sinapsis-AI/sinapsis-langchain.git
Requires-Python: >=3.10
License-File: LICENSE
Requires-Dist: sinapsis>=0.1.1
Provides-Extra: all
Requires-Dist: sinapsis-langchain-readers[all]; extra == "all"
Requires-Dist: sinapsis-langchain-splitters; extra == "all"
Dynamic: license-file
